chatminer/__init__.py
chatminer/chatparsers.py
chatminer/cli.py
chatminer/visualizations.py
chat_miner-0.6.0.dist-info/METADATA
chat_miner-0.6.0.dist-info/WHEEL
chat_miner-0.6.0.dist-info/entry_points.txt
chat_miner-0.6.0.dist-info/licenses/LICENSE
chat_miner-0.6.0.dist-info/RECORD
