Metadata-Version: 2.4
Name: chat-miner
Version: 0.6.0
Summary: Lean parsers and visualizations for chat data.
Project-URL: Bug Tracker, https://github.com/joweich/chat-miner/issues
Project-URL: Source Code, https://github.com/joweich/chat-miner
Author-email: Jonas Weich <jns.wch@gmail.com>
Maintainer-email: Jonas Weich <jns.wch@gmail.com>
License-Expression: MIT
License-File: LICENSE
Keywords: chat,chatdata,messenger,parser,wordcloud
Classifier: Development Status :: 5 - Production/Stable
Classifier: Environment :: Console
Classifier: Intended Audience :: End Users/Desktop
Classifier: Intended Audience :: Science/Research
Classifier: License :: OSI Approved :: MIT License
Classifier: Operating System :: OS Independent
Classifier: Programming Language :: Python
Classifier: Programming Language :: Python :: 3
Classifier: Programming Language :: Python :: 3 :: Only
Classifier: Programming Language :: Python :: 3.8
Classifier: Programming Language :: Python :: 3.9
Classifier: Programming Language :: Python :: 3.10
Classifier: Programming Language :: Python :: 3.11
Classifier: Programming Language :: Python :: 3.12
Requires-Python: >=3.8
Requires-Dist: argparse
Requires-Dist: matplotlib>=3.4
Requires-Dist: numpy>=1.6.1
Requires-Dist: polars[pandas]>=1.0
Requires-Dist: python-dateutil>=2.8.2
Requires-Dist: tqdm>=4.66.0
Requires-Dist: wordcloud>=1.9.3
